deltachat_faqbot/__init__.py
deltachat_faqbot/__main__.py
deltachat_faqbot/_version.py
deltachat_faqbot/hooks.py
deltachat_faqbot/orm.py
deltachat_faqbot/utils.py
deltachat_faqbot-0.7.0.dist-info/LICENSE.txt
deltachat_faqbot-0.7.0.dist-info/METADATA
deltachat_faqbot-0.7.0.dist-info/WHEEL
deltachat_faqbot-0.7.0.dist-info/entry_points.txt
deltachat_faqbot-0.7.0.dist-info/top_level.txt
deltachat_faqbot-0.7.0.dist-info/RECORD
